aws_lambda_layer/__init__.py
aws_lambda_layer/_version.py
aws_lambda_layer/api.py
aws_lambda_layer/context.py
aws_lambda_layer/layer.py
aws_lambda_layer/source.py
aws_lambda_layer/test.txt
aws_lambda_layer/utils.py
aws_lambda_layer/vendor/__init__.py
aws_lambda_layer/vendor/better_pathlib.py
aws_lambda_layer/vendor/build_dist.py
aws_lambda_layer/vendor/hashes.py
aws_lambda_layer-0.5.3.dist-info/AUTHORS.rst
aws_lambda_layer-0.5.3.dist-info/LICENSE.txt
aws_lambda_layer-0.5.3.dist-info/METADATA
aws_lambda_layer-0.5.3.dist-info/WHEEL
aws_lambda_layer-0.5.3.dist-info/RECORD
