Metadata-Version: 2.1
Name: aws_lambda_layer
Version: 0.5.3
Summary: A simple tool that automates the process of building and deploying AWS Lambda layers and source artifacts.
Author: Sanhe Hu
Author-email: husanhe@gmail.com
Requires-Python: >=3.7,<4.0
Classifier: Programming Language :: Python :: 3
Classifier: Programming Language :: Python :: 3.7
Classifier: Programming Language :: Python :: 3.8
Classifier: Programming Language :: Python :: 3.9
Classifier: Programming Language :: Python :: 3.10
Classifier: Programming Language :: Python :: 3.11
Classifier: Programming Language :: Python :: 3.12
Requires-Dist: boto3
Requires-Dist: s3pathlib (>=2.0.1,<3.0.0)
